atdcheck/ATD.py
atdcheck/__init__.py
atdcheck/__main__.py
atdcheck/atdcheck.py
atdcheck-1.0.4.dist-info/DESCRIPTION.rst
atdcheck-1.0.4.dist-info/METADATA
atdcheck-1.0.4.dist-info/RECORD
atdcheck-1.0.4.dist-info/WHEEL
atdcheck-1.0.4.dist-info/entry_points.txt
atdcheck-1.0.4.dist-info/metadata.json
atdcheck-1.0.4.dist-info/top_level.txt
